pybd_decrypt/__init__.py
pybd_decrypt/data.py
pybd_decrypt-1.0.1.dist-info/METADATA
pybd_decrypt-1.0.1.dist-info/WHEEL
pybd_decrypt-1.0.1.dist-info/top_level.txt
pybd_decrypt-1.0.1.dist-info/RECORD
